pycompgen/__init__.py
pycompgen/analyzers.py
pycompgen/cache.py
pycompgen/detectors.py
pycompgen/generators.py
pycompgen/logger.py
pycompgen/models.py
pycompgen/py.typed
pycompgen-0.2.0.dist-info/METADATA
pycompgen-0.2.0.dist-info/WHEEL
pycompgen-0.2.0.dist-info/entry_points.txt
pycompgen-0.2.0.dist-info/licenses/LICENSE
pycompgen-0.2.0.dist-info/RECORD
