Metadata-Version: 2.4
Name: pycompgen
Version: 0.2.0
Summary: Generate shell completions automatically
Author-email: Adrian Vollmer <av3@mailbox.org>
License-File: LICENSE
Requires-Python: >=3.11
